scripts/__init__.py
scripts/_utils.py
scripts/cli.py
scripts/convert_Rdata.py
scripts/main.py
stadiffuser/__init__.py
stadiffuser/analytics.py
stadiffuser/cli.py
stadiffuser/dataset.py
stadiffuser/metrics.py
stadiffuser/misc.py
stadiffuser/models.py
stadiffuser/modules.py
stadiffuser/pipeline.py
stadiffuser/utils.py
stadiffuser/vae.py
stadiffuser-0.1.1.dist-info/LICENSE.txt
stadiffuser-0.1.1.dist-info/METADATA
stadiffuser-0.1.1.dist-info/WHEEL
stadiffuser-0.1.1.dist-info/entry_points.txt
stadiffuser-0.1.1.dist-info/top_level.txt
stadiffuser-0.1.1.dist-info/RECORD
